vidrial-0.2.1.data/purelib/vidrial/__init__.py
vidrial-0.2.1.data/purelib/vidrial/cuda_utils/ABC_utils.cuh
vidrial-0.2.1.data/purelib/vidrial/cuda_utils/allocator.cuh
vidrial-0.2.1.data/purelib/vidrial/cuda_utils/copy.cuh
vidrial-0.2.1.data/purelib/vidrial/cuda_utils/frg_copy.cuh
vidrial-0.2.1.data/purelib/vidrial/cuda_utils/frgthr_tiling.cuh
vidrial-0.2.1.data/purelib/vidrial/cuda_utils/gemm.cuh
vidrial-0.2.1.data/purelib/vidrial/cuda_utils/launch.cuh
vidrial-0.2.1.data/purelib/vidrial/cuda_utils/mask_cfg.cuh
vidrial-0.2.1.data/purelib/vidrial/cuda_utils/perf_cfg.cuh
vidrial-0.2.1.data/purelib/vidrial/cuda_utils/pipeline.cuh
vidrial-0.2.1.data/purelib/vidrial/cuda_utils/softmax.cuh
vidrial-0.2.1.data/purelib/vidrial/cuda_utils/swizzle_cfg.cuh
vidrial-0.2.1.data/purelib/vidrial/cuda_utils/sympow.cuh
vidrial-0.2.1.data/purelib/vidrial/cuda_utils/tprod.cuh
vidrial-0.2.1.data/purelib/vidrial/cuda_utils/utilities.cuh
vidrial-0.2.1.data/purelib/vidrial/cuda_utils/tests/copy_test.cu
vidrial-0.2.1.data/purelib/vidrial/cuda_utils/tests/frgthr_tiling_test.cu
vidrial-0.2.1.data/purelib/vidrial/cuda_utils/tests/ldsm_test.cu
vidrial-0.2.1.data/purelib/vidrial/cuda_utils/tests/swizzle_test.cu
vidrial-0.2.1.data/purelib/vidrial/cuda_utils/tests/tprod_test.cu
vidrial-0.2.1.data/purelib/vidrial/cuda_utils/tests/utils_test.cu
vidrial-0.2.1.data/purelib/vidrial/jit/__init__.py
vidrial-0.2.1.data/purelib/vidrial/jit/binding.py
vidrial-0.2.1.data/purelib/vidrial/jit/compiler.py
vidrial-0.2.1.data/purelib/vidrial/jit/ctypes.py
vidrial-0.2.1.data/purelib/vidrial/jit/jit.py
vidrial-0.2.1.data/purelib/vidrial/jit/package.py
vidrial-0.2.1.data/purelib/vidrial/jit/runtime.py
vidrial-0.2.1.data/purelib/vidrial/jit/settings.py
vidrial-0.2.1.data/purelib/vidrial/jit/timer.py
vidrial-0.2.1.data/purelib/vidrial/jit/timing.py
vidrial-0.2.1.data/purelib/vidrial/jit/timingcache.py
vidrial-0.2.1.data/purelib/vidrial/jit/tuner.py
vidrial-0.2.1.data/purelib/vidrial/jit/viz.py
vidrial-0.2.1.dist-info/licenses/LICENSE
vidrial-0.2.1.dist-info/METADATA
vidrial-0.2.1.dist-info/WHEEL
vidrial-0.2.1.dist-info/top_level.txt
vidrial-0.2.1.dist-info/RECORD
