Metadata-Version: 2.4
Name: vidrial
Version: 0.2.1
Summary: Library containing vidrial framework and associated kernels
Author-email: Carles Gelada <carles@manifestai.com>, Sean Zhang <sean@manifestai.com>, Jacob Buckman <jacob@manifestai.com>
Requires-Python: >=3.11
License-File: LICENSE
Requires-Dist: torch>=2.0.0
Requires-Dist: numpy>=2.2.0
Requires-Dist: tabulate>=0.9.0
Requires-Dist: tqdm>=4.67.1
Requires-Dist: pyyaml>=6.0.2
Requires-Dist: click>=8.1.3
Dynamic: license-file
